LICENSE
README.md
setup.py
care2omop/__init__.py
care2omop/auth.py
care2omop/main.py
care2omop/utils.py
care2omop.egg-info/PKG-INFO
care2omop.egg-info/SOURCES.txt
care2omop.egg-info/dependency_links.txt
care2omop.egg-info/top_level.txt