Metadata-Version: 2.1
Name: care2omop
Version: 0.0.2
Summary: Mapping CARE-SM to OMOP-CDM
Home-page: https://github.com/CARE-SM/CARE2OMOP
Author: Pablo Alarcón Moreno
Author-email: pabloalarconmoreno@gmail.com
License: MIT
Keywords: EJP-RD,EJP,CARE-SM,OMOP,CARE
Platform: UNKNOWN
License-File: LICENSE
